rxndb/__init__.py
rxndb/data_loader.py
rxndb_bench-0.0.3.dist-info/METADATA
rxndb_bench-0.0.3.dist-info/WHEEL
rxndb_bench-0.0.3.dist-info/licenses/LICENSE
rxndb_bench-0.0.3.dist-info/RECORD
